concierge_types/__init__.py
concierge_types/exceptions.py
concierge_types/models.py
concierge_types-0.1a2.dist-info/METADATA
concierge_types-0.1a2.dist-info/WHEEL
concierge_types-0.1a2.dist-info/RECORD
